gcide/__init__.py
gcide/cmds.py
gcide/fnd.py
gcide/hdl.py
gcide/irc.py
gcide/mbx.py
gcide/mdl.py
gcide/obj.py
gcide/req.py
gcide/rss.py
gcide/slg.py
gcide/thr.py
gcide/udp.py
gcide/utl.py
gcide/wsd.py
gcide-100.data/data/share/doc/gcide/ECHAabilify.png
gcide-100.data/data/share/doc/gcide/ECHAclozapine.png
gcide-100.data/data/share/doc/gcide/ECHAhaldol.png
gcide-100.data/data/share/doc/gcide/ECHAzyprexa.png
gcide-100.data/data/share/doc/gcide/EM_T04_OTP-CR-117_19.pdf
gcide-100.data/data/share/doc/gcide/EM_T07_OTP-CR-117_19_001.pdf
gcide-100.data/data/share/doc/gcide/Kamer.pdf
gcide-100.data/data/share/doc/gcide/OTP1.png
gcide-100.data/data/share/doc/gcide/OTP2.png
gcide-100.data/data/share/doc/gcide/about.rst
gcide-100.data/data/share/doc/gcide/base.rst
gcide-100.data/data/share/doc/gcide/bevestigd.jpg
gcide-100.data/data/share/doc/gcide/bevestigd.pdf
gcide-100.data/data/share/doc/gcide/class.rst
gcide-100.data/data/share/doc/gcide/conf.py
gcide-100.data/data/share/doc/gcide/evidence.rst
gcide-100.data/data/share/doc/gcide/gcide.css
gcide-100.data/data/share/doc/gcide/genocide.png
gcide-100.data/data/share/doc/gcide/guilty.rst
gcide-100.data/data/share/doc/gcide/index.rst
gcide-100.data/data/share/doc/gcide/informed.jpg
gcide-100.data/data/share/doc/gcide/kamer.png
gcide-100.data/data/share/doc/gcide/manual.rst
gcide-100.data/data/share/doc/gcide/module.rst
gcide-100.data/data/share/doc/gcide/reconsider.rst
gcide-100.data/data/share/doc/gcide/request.rst
gcide-100.data/data/share/doc/gcide/skull.jpg
gcide-100.data/data/share/doc/gcide/skullagain.jpg
gcide-100.data/data/share/doc/gcide/skullnr.jpg
gcide-100.data/data/share/doc/gcide/skullnr2.jpg
gcide-100.data/data/share/doc/gcide/source.rst
gcide-100.data/data/share/doc/gcide/writings.rst
gcide-100.data/data/share/doc/gcide/_static/gcide.css
gcide-100.data/data/share/doc/gcide/_templates/base.rst
gcide-100.data/data/share/doc/gcide/_templates/class.rst
gcide-100.data/data/share/doc/gcide/_templates/module.rst
gcide-100.dist-info/METADATA
gcide-100.dist-info/WHEEL
gcide-100.dist-info/top_level.txt
gcide-100.dist-info/zip-safe
gcide-100.dist-info/RECORD
