Metadata-Version: 2.1
Name: gcide
Version: 100
Summary: Court. Prosecutor. Reconsider OTP-CR-117/19.
Home-page: https://github.com/operbot/gcide
Author: Bart Thate
Author-email: operbot100@gmail.com
License: Public Domain
Classifier: Development Status :: 3 - Alpha
Classifier: License :: Public Domain
Classifier: Operating System :: Unix
Classifier: Programming Language :: Python
Classifier: Topic :: Utilities
